dateutil-stubs/METADATA.toml
dateutil-stubs/__init__.pyi
dateutil-stubs/_common.pyi
dateutil-stubs/_version.pyi
dateutil-stubs/easter.pyi
dateutil-stubs/py.typed
dateutil-stubs/relativedelta.pyi
dateutil-stubs/rrule.pyi
dateutil-stubs/tzwin.pyi
dateutil-stubs/utils.pyi
dateutil-stubs/parser/__init__.pyi
dateutil-stubs/parser/_parser.pyi
dateutil-stubs/parser/isoparser.pyi
dateutil-stubs/tz/__init__.pyi
dateutil-stubs/tz/_common.pyi
dateutil-stubs/tz/tz.pyi
dateutil-stubs/tz/win.pyi
dateutil-stubs/zoneinfo/__init__.pyi
dateutil-stubs/zoneinfo/rebuild.pyi
types_python_dateutil-2.9.0.20251108.dist-info/licenses/LICENSE
types_python_dateutil-2.9.0.20251108.dist-info/METADATA
types_python_dateutil-2.9.0.20251108.dist-info/WHEEL
types_python_dateutil-2.9.0.20251108.dist-info/top_level.txt
types_python_dateutil-2.9.0.20251108.dist-info/RECORD
